goat_pypi_project-0.1.1.dist-info/licenses/LICENSE
tests/__init__.py
tests/test_main.py
goat_pypi_project-0.1.1.dist-info/METADATA
goat_pypi_project-0.1.1.dist-info/WHEEL
goat_pypi_project-0.1.1.dist-info/top_level.txt
goat_pypi_project-0.1.1.dist-info/RECORD
