Metadata-Version: 2.4
Name: goat-pypi-project
Version: 0.1.1
Summary: A Python package for goat-related functionalities.
Home-page: https://github.com/yourusername/goat-pypi-project
Author: Daniel Nebenzahl
Author-email: Daniel Nebenzahl <dn@scribesecurity.com>
License-Expression: MIT
Keywords: goat,pypi,python,package
Classifier: Programming Language :: Python :: 3
Classifier: Operating System :: OS Independent
Requires-Python: >=3.6
License-File: LICENSE
Dynamic: author
Dynamic: home-page
Dynamic: license-file
Dynamic: requires-python
